majestic/__main__.py
majestic/cli/__init__.py
majestic_cli-0.2601.0.dist-info/METADATA
majestic_cli-0.2601.0.dist-info/WHEEL
majestic_cli-0.2601.0.dist-info/top_level.txt
majestic_cli-0.2601.0.dist-info/RECORD
