Metadata-Version: 2.4
Name: majestic-cli
Version: 0.2601.0
Summary: CLI tool for Majestic
Author-email: Kairix Devteam <devteam@kairix.dev>
Requires-Python: >=3.12
